bobtemplates.pypbr-0.3-py2.7-nspkg.pth
bobtemplates/pypbr/__init__.py
bobtemplates/pypbr/hooks.py
bobtemplates/pypbr/namespace_package/.mrbob.ini
bobtemplates/pypbr/namespace_package/python-+python.module.name+-+python.module.namespace.name+/.gitignore
bobtemplates/pypbr/namespace_package/python-+python.module.name+-+python.module.namespace.name+/LICENSE
bobtemplates/pypbr/namespace_package/python-+python.module.name+-+python.module.namespace.name+/MANIFEST.in
bobtemplates/pypbr/namespace_package/python-+python.module.name+-+python.module.namespace.name+/README.rst.bob
bobtemplates/pypbr/namespace_package/python-+python.module.name+-+python.module.namespace.name+/setup.cfg.bob
bobtemplates/pypbr/namespace_package/python-+python.module.name+-+python.module.namespace.name+/setup.py.bob
bobtemplates/pypbr/namespace_package/python-+python.module.name+-+python.module.namespace.name+/+python.module.name+/__init__.py
bobtemplates/pypbr/namespace_package/python-+python.module.name+-+python.module.namespace.name+/+python.module.name+/+python.module.namespace.name+/__init__.py
bobtemplates/pypbr/package/.mrbob.ini
bobtemplates/pypbr/package/python-+python.module.name+/.gitignore
bobtemplates/pypbr/package/python-+python.module.name+/LICENSE
bobtemplates/pypbr/package/python-+python.module.name+/MANIFEST.in
bobtemplates/pypbr/package/python-+python.module.name+/README.rst.bob
bobtemplates/pypbr/package/python-+python.module.name+/setup.cfg.bob
bobtemplates/pypbr/package/python-+python.module.name+/setup.py.bob
bobtemplates/pypbr/package/python-+python.module.name+/+python.module.name+/__init__.py
bobtemplates/pypbr/tests/test_hooks.py
bobtemplates.pypbr-0.3.dist-info/DESCRIPTION.rst
bobtemplates.pypbr-0.3.dist-info/METADATA
bobtemplates.pypbr-0.3.dist-info/metadata.json
bobtemplates.pypbr-0.3.dist-info/namespace_packages.txt
bobtemplates.pypbr-0.3.dist-info/RECORD
bobtemplates.pypbr-0.3.dist-info/top_level.txt
bobtemplates.pypbr-0.3.dist-info/WHEEL
